LICENSE
README.md
setup.cfg
setup.py
notetaker/__init__.py
notetaker.egg-info/PKG-INFO
notetaker.egg-info/SOURCES.txt
notetaker.egg-info/dependency_links.txt
notetaker.egg-info/top_level.txt
notetaker/etc/nbextension.json
notetaker/static/main.js