Metadata-Version: 1.0
Name: notetaker
Version: 0.0.6
Summary: Jupyter Notebook extension to record history
Home-page: https://github.com/yifanwu/notetaker
Author: Yifan Wu
Author-email: UNKNOWN
License: UNKNOWN
Platform: UNKNOWN
